[1,["11LI9tAkhJwaVDDY8B6/m3"],0,[["sp.SkeletonData",["_name","_atlasText","textureNames","_skeletonJson","textures"],-1,3]],[[0,0,1,2,3,4,5]],[[0,"tu_biao","\ntu_biao.png\nsize: 1493,1517\nformat: RGBA8888\nfilter: Linear,Linear\nrepeat: none\nA_guang_quan\n  rotate: true\n  xy: 1118, 249\n  size: 239, 238\n  orig: 241, 242\n  offset: 0, 2\n  index: -1\nA_hong1\n  rotate: true\n  xy: 521, 490\n  size: 517, 495\n  orig: 604, 543\n  offset: 41, 48\n  index: -1\nA_hong2\n  rotate: false\n  xy: 1118, 162\n  size: 325, 85\n  orig: 325, 85\n  offset: 0, 0\n  index: -1\nA_hong3\n  rotate: false\n  xy: 1429, 1070\n  size: 22, 22\n  orig: 24, 24\n  offset: 1, 1\n  index: -1\nA_hong4\n  rotate: false\n  xy: 839, 211\n  size: 277, 277\n  orig: 277, 277\n  offset: 0, 0\n  index: -1\nA_hong5\n  rotate: false\n  xy: 842, 2\n  size: 208, 207\n  orig: 208, 207\n  offset: 0, 0\n  index: -1\nA_hong6\n  rotate: true\n  xy: 1368, 4\n  size: 156, 71\n  orig: 156, 71\n  offset: 0, 0\n  index: -1\nA_jin1\n  rotate: true\n  xy: 1018, 490\n  size: 517, 473\n  orig: 604, 521\n  offset: 41, 48\n  index: -1\nA_jin2\n  rotate: true\n  xy: 1395, 1190\n  size: 325, 85\n  orig: 325, 85\n  offset: 0, 0\n  index: -1\nA_jin3\n  rotate: false\n  xy: 1429, 1094\n  size: 22, 22\n  orig: 24, 24\n  offset: 1, 1\n  index: -1\nA_jin4\n  rotate: false\n  xy: 560, 211\n  size: 277, 277\n  orig: 277, 277\n  offset: 0, 0\n  index: -1\nA_jin5\n  rotate: false\n  xy: 632, 2\n  size: 208, 207\n  orig: 208, 207\n  offset: 0, 0\n  index: -1\nA_jin6\n  rotate: false\n  xy: 1210, 89\n  size: 156, 71\n  orig: 156, 71\n  offset: 0, 0\n  index: -1\nA_lian1\n  rotate: false\n  xy: 2, 490\n  size: 517, 506\n  orig: 604, 554\n  offset: 41, 48\n  index: -1\nA_lian2\n  rotate: false\n  xy: 1029, 1103\n  size: 325, 85\n  orig: 325, 85\n  offset: 0, 0\n  index: -1\nA_lian3\n  rotate: false\n  xy: 1429, 1142\n  size: 22, 22\n  orig: 24, 24\n  offset: 1, 1\n  index: -1\nA_lian4\n  rotate: false\n  xy: 2, 211\n  size: 277, 277\n  orig: 277, 277\n  offset: 0, 0\n  index: -1\nA_lian5\n  rotate: false\n  xy: 212, 2\n  size: 208, 207\n  orig: 208, 207\n  offset: 0, 0\n  index: -1\nA_lian6\n  rotate: true\n  xy: 1358, 332\n  size: 156, 71\n  orig: 156, 71\n  offset: 0, 0\n  index: -1\nA_lv1\n  rotate: true\n  xy: 2, 998\n  size: 517, 506\n  orig: 604, 554\n  offset: 41, 48\n  index: -1\nA_lv2\n  rotate: true\n  xy: 1029, 1190\n  size: 325, 85\n  orig: 325, 85\n  offset: 0, 0\n  index: -1\nA_lv3\n  rotate: false\n  xy: 1429, 1166\n  size: 22, 22\n  orig: 24, 24\n  offset: 1, 1\n  index: -1\nA_lv4\n  rotate: false\n  xy: 1116, 1238\n  size: 277, 277\n  orig: 277, 277\n  offset: 0, 0\n  index: -1\nA_lv5\n  rotate: false\n  xy: 2, 2\n  size: 208, 207\n  orig: 208, 207\n  offset: 0, 0\n  index: -1\nA_lv6\n  rotate: true\n  xy: 1356, 1032\n  size: 156, 71\n  orig: 156, 71\n  offset: 0, 0\n  index: -1\nA_zi1\n  rotate: false\n  xy: 510, 1009\n  size: 517, 506\n  orig: 604, 554\n  offset: 41, 48\n  index: -1\nA_zi2\n  rotate: false\n  xy: 1029, 1016\n  size: 325, 85\n  orig: 325, 85\n  offset: 0, 0\n  index: -1\nA_zi3\n  rotate: false\n  xy: 1429, 1118\n  size: 22, 22\n  orig: 24, 24\n  offset: 1, 1\n  index: -1\nA_zi4\n  rotate: false\n  xy: 281, 211\n  size: 277, 277\n  orig: 277, 277\n  offset: 0, 0\n  index: -1\nA_zi5\n  rotate: false\n  xy: 422, 2\n  size: 208, 207\n  orig: 208, 207\n  offset: 0, 0\n  index: -1\nA_zi6\n  rotate: false\n  xy: 1052, 89\n  size: 156, 71\n  orig: 156, 71\n  offset: 0, 0\n  index: -1\n",["tu_biao.png"],{"skeleton":{"hash":"8pBwSWbP9NpqzQQp32P+yvpLjhM","spine":"3.8.75","x":-301.55,"y":310.83,"width":604,"height":554},"bones":[{"name":"root"},{"name":"bone","parent":"root","x":-2.27,"y":614.64},{"name":"A_lv1_wu_qi","parent":"bone","x":0.85,"y":-2.06},{"name":"A_lv4","parent":"bone","x":1.94,"y":-2.41},{"name":"bone2","parent":"bone","x":125.63,"y":-130.11},{"name":"bone3","parent":"bone2","x":-131.36,"y":3.75},{"name":"bone4","parent":"bone2","x":-42.52,"y":7.2},{"name":"bone5","parent":"bone2","x":131.18,"y":-12.19},{"name":"bone6","parent":"bone2","x":41.1,"y":10.22},{"name":"A_lv6","parent":"bone","x":-160.68,"y":2.09},{"name":"A_lv7","parent":"A_lv6","x":-80.7,"y":60.37},{"name":"A_lv8","parent":"A_lv6","x":-20.94,"y":57.29},{"name":"A_lv9","parent":"A_lv6","x":53.9,"y":65.6},{"name":"bone7","parent":"root","x":-1.43,"y":613.33},{"name":"A_lv3","parent":"A_lv4","x":69.22,"y":119.35}],"slots":[{"name":"A_lv6","bone":"A_lv6","attachment":"A_lv6"},{"name":"A_lv25","bone":"A_lv6","attachment":"A_lv6"},{"name":"A_lv20","bone":"A_lv6","attachment":"A_lv6"},{"name":"A_lv15","bone":"A_lv6","attachment":"A_lv6"},{"name":"A_lv10","bone":"A_lv6","attachment":"A_lv6"},{"name":"A_lv5","bone":"bone","attachment":"A_lv5"},{"name":"A_lv22","bone":"bone","attachment":"A_lv5"},{"name":"A_lv17","bone":"bone","attachment":"A_lv5"},{"name":"A_lv12","bone":"bone","attachment":"A_lv5"},{"name":"A_lv7","bone":"bone","attachment":"A_lv5"},{"name":"A_lv4","bone":"A_lv4","attachment":"A_lv4"},{"name":"A_lv23","bone":"A_lv4","attachment":"A_lv4"},{"name":"A_lv18","bone":"A_lv4","attachment":"A_lv4"},{"name":"A_lv13","bone":"A_lv4","attachment":"A_lv4"},{"name":"A_lv9","bone":"A_lv4","attachment":"A_lv4"},{"name":"A_lv3","bone":"A_lv3","attachment":"A_lv3"},{"name":"A_lv24","bone":"A_lv3","attachment":"A_lv3"},{"name":"A_lv19","bone":"A_lv3","attachment":"A_lv3"},{"name":"A_lv14","bone":"A_lv3","attachment":"A_lv3"},{"name":"A_lv8","bone":"A_lv3","attachment":"A_lv3"},{"name":"A_lv2","bone":"bone2","attachment":"A_lv2"},{"name":"A_lv26","bone":"bone2","attachment":"A_lv2"},{"name":"A_lv21","bone":"bone2","attachment":"A_lv2"},{"name":"A_lv16","bone":"bone2","attachment":"A_lv2"},{"name":"A_lv11","bone":"bone2","attachment":"A_lv2"},{"name":"A_lv1_wu_qi","bone":"A_lv1_wu_qi","attachment":"A_lv1"},{"name":"A_lv1_wu_qi5","bone":"A_lv1_wu_qi","attachment":"A_lv1"},{"name":"A_lv1_wu_qi4","bone":"A_lv1_wu_qi","attachment":"A_lv1"},{"name":"A_lv1_wu_qi3","bone":"A_lv1_wu_qi","attachment":"A_lv1"},{"name":"A_lv1_wu_qi2","bone":"A_lv1_wu_qi","attachment":"A_lv1"},{"name":"A_guang_quan","bone":"bone7","attachment":"A_guang_quan"},{"name":"A_guang_quan2","bone":"bone7","attachment":"A_guang_quan"},{"name":"A_guang_quan3","bone":"bone7","attachment":"A_guang_quan"},{"name":"A_guang_quan4","bone":"bone7","attachment":"A_guang_quan"},{"name":"A_guang_quan5","bone":"bone7","attachment":"A_guang_quan"}],"skins":[{"name":"0","attachments":{"A_guang_quan":{"A_guang_quan":{"color":"b8ffb8ff","x":3.25,"y":3.32,"width":241,"height":242}},"A_lv1_wu_qi":{"A_lv1":{"x":1.87,"y":-24.76,"width":604,"height":554}},"A_lv2":{"A_lv2":{"type":"mesh","hull":19,"uvs":[1,0.75149,1,1,0.875,1,0.75,1,0.625,1,0.5,1,0.375,1,0.25,1,0.112,0.85092,0.00001,0.85091,0,0.44725,0.11038,0.27332,0.23375,0.20499,0.36525,0.24226,0.5,0,0.625,0,0.75,0,0.85875,0.44725,0.99513,0.52179,0.1147,0.61483,0.23979,0.62105,0.37301,0.5962,0.50623,0.47818,0.62645,0.54651,0.73205,0.67074,0.87664,0.8074],"triangles":[7,8,20,8,19,20,8,9,19,9,10,19,20,11,12,10,11,19,20,19,11,22,5,21,7,21,6,5,6,21,7,20,21,20,13,21,20,12,13,21,13,22,13,14,22,4,24,3,4,23,24,4,5,23,5,22,23,17,24,16,22,15,23,24,23,16,23,15,16,22,14,15,2,25,1,25,0,1,2,3,25,3,24,25,24,17,25,25,18,0,25,17,18],"vertices":[1,7,26.25,3.34,1,1,7,26.25,-17.79,1,2,7,-14.17,-17.82,0.98787,8,58.67,-37.64,0.01213,2,7,-46.58,-19.05,0.5116,8,26.26,-38.88,0.4884,3,7,-79.42,-20.22,0.05978,8,-6.58,-40.04,0.85015,6,77.03,-37.03,0.09006,2,8,-46.17,-40.2,0.44108,6,37.44,-37.18,0.55892,3,8,-86.8,-40.2,0.04131,6,-3.19,-37.18,0.90163,5,85.66,-33.73,0.05707,2,6,-43.81,-37.18,0.58793,5,45.03,-33.73,0.41207,2,6,-88.66,-24.51,0.04446,5,0.18,-21.06,0.95554,1,5,-36.21,-21.06,1,1,5,-36.22,13.25,1,2,6,-89.19,24.59,0.05116,5,-0.34,28.03,0.94884,2,6,-49.09,30.39,0.48238,5,39.75,33.84,0.51762,3,8,-89.97,24.21,0.04001,6,-6.35,27.23,0.90354,5,82.49,30.67,0.05644,2,8,-46.17,44.8,0.54187,6,37.44,47.82,0.45813,3,7,-78.64,64.67,0.0148,8,-5.81,44.84,0.89048,6,77.81,47.86,0.09472,3,7,-40.94,65.1,0.18442,8,31.9,45.28,0.8155,6,115.51,48.3,0.00008,2,7,-16.58,28.74,0.82165,8,56.25,8.91,0.17835,1,7,24.66,22.86,1,2,6,-87.78,-4.44,0.00574,5,1.06,-0.99,0.99426,2,6,-47.13,-4.97,0.50855,5,41.72,-1.52,0.49145,2,6,-3.83,-2.86,0.97987,5,85.01,0.59,0.02013,2,8,-44.15,4.16,0.49196,6,39.46,7.17,0.50804,2,8,-5.08,-1.65,0.97378,6,78.54,1.37,0.02622,2,7,-49.73,8.54,0.35602,8,23.1,-11.29,0.64398,1,7,-13.85,-1.42,1]}},"A_lv3":{"A_lv3":{"x":0.12,"y":-0.43,"width":24,"height":24}},"A_lv4":{"A_lv4":{"x":-0.01,"y":0.81,"width":277,"height":277}},"A_lv5":{"A_lv5":{"x":3.41,"y":1.03,"width":208,"height":207}},"A_lv6":{"A_lv6":{"type":"mesh","hull":22,"uvs":[1,0.2532,1,0.45133,0.89019,0.40863,0.78981,0.81189,0.70425,0.90922,0.62446,0.99999,0.43995,0.98614,0.39523,0.87313,0.30029,0.63324,0.16994,0.60332,0,0.41327,0,0.23528,0,0,0.2,0,0.28824,0,0.4,0,0.5069,0,0.6,0,0.70875,0,0.8,0,0.89167,0,0.99999,0.00001,0.0613,0.30695,0.19584,0.3383,0.38134,0.32486,0.58518,0.401,0.79922,0.32934,0.5158,0.75106,0.29875,0.31147,0.47326,0.44544,0.68983,0.41311,0.60572,0.73649],"triangles":[22,11,12,13,22,12,28,14,15,24,28,15,26,18,19,23,22,13,25,16,17,20,26,19,2,26,20,0,2,20,0,20,21,30,17,18,30,18,26,25,17,30,10,11,22,16,24,15,29,16,25,29,24,16,1,2,0,9,22,23,10,22,9,8,28,24,8,24,29,13,14,28,28,23,13,8,23,28,9,23,8,31,25,30,27,29,25,31,27,25,7,8,29,3,30,26,3,26,2,31,30,3,27,7,29,4,31,3,6,7,27,5,31,4,27,31,5,6,27,5],"vertices":[1,12,16.85,-2.36,1,1,12,16.85,-16.43,1,2,12,-0.23,-13.38,0.99623,11,59.52,-9.37,0.00377,2,12,-11.9,-40.87,0.73223,11,47.85,-36.87,0.26777,2,12,-22.77,-47.07,0.56771,11,36.99,-43.07,0.43229,2,12,-32.97,-52.87,0.41882,11,26.78,-48.87,0.58118,3,12,-58.2,-50.88,0.18343,11,1.55,-46.87,0.81638,10,61.31,-49.95,0.00019,3,12,-64.37,-42.62,0.1301,11,-4.62,-38.62,0.86361,10,55.13,-41.7,0.00629,3,12,-77.39,-25.08,0.01154,11,-17.64,-21.07,0.82026,10,42.11,-24.15,0.1682,2,11,-37.8,-18.9,0.44257,10,21.95,-21.98,0.55743,2,11,-64.31,-5.41,0.00759,10,-4.56,-8.49,0.9924,1,10,-4.56,4.15,1,2,11,-64.31,23.94,0.00708,10,-4.56,20.86,0.99292,2,11,-33.11,23.94,0.42776,10,26.64,20.86,0.57224,2,11,-19.35,23.94,0.70252,10,40.41,20.86,0.29748,3,12,-62.1,19.8,0.02934,11,-2.35,23.81,0.90853,10,57.4,20.73,0.06212,3,12,-48.1,19.04,0.20654,11,11.65,23.04,0.79213,10,71.4,19.96,0.00133,2,12,-37.69,17.87,0.47874,11,22.06,21.87,0.52126,2,12,-25.75,16.43,0.81197,11,34,20.43,0.18803,2,12,-13.94,15.74,0.97289,11,45.81,19.74,0.02711,1,12,-0.05,15.62,1,1,12,16.84,15.62,1,2,11,-54.75,2.14,0.04888,10,5,-0.94,0.95112,2,11,-33.76,-0.08,0.44437,10,25.99,-3.16,0.55563,2,11,-4.82,0.87,0.95795,10,54.93,-2.21,0.04205,2,12,-38.95,-10.3,0.40894,11,20.81,-6.3,0.59106,2,12,-14.33,-7.72,0.99037,11,45.42,-3.72,0.00963,2,12,-47.32,-34.46,0.24672,11,12.43,-30.45,0.75328,2,11,-17.71,1.82,0.76277,10,42.05,-1.26,0.23723,3,12,-52,-12.2,0.11679,11,7.76,-8.2,0.88319,10,67.51,-11.28,0.00002,2,12,-27.38,-12.52,0.72459,11,32.37,-8.52,0.27541,2,12,-36,-34.2,0.42591,11,23.76,-30.19,0.57409]}}}},{"name":"1","attachments":{"A_guang_quan2":{"A_guang_quan":{"color":"7693ffff","x":3.25,"y":3.32,"width":241,"height":242}},"A_lv1_wu_qi2":{"A_lv1":{"path":"A_lian1","x":1.87,"y":-24.76,"width":604,"height":554}},"A_lv10":{"A_lv6":{"type":"mesh","path":"A_lian6","hull":22,"uvs":[1,0.2532,1,0.45133,0.89019,0.40863,0.78981,0.81189,0.70425,0.90922,0.62446,0.99999,0.43995,0.98614,0.39523,0.87313,0.30029,0.63324,0.16994,0.60332,0,0.41327,0,0.23528,0,0,0.2,0,0.28824,0,0.4,0,0.5069,0,0.6,0,0.70875,0,0.8,0,0.89167,0,0.99999,0.00001,0.0613,0.30695,0.19584,0.3383,0.38134,0.32486,0.58518,0.401,0.79922,0.32934,0.5158,0.75106,0.29875,0.31147,0.47326,0.44544,0.68983,0.41311,0.60572,0.73649],"triangles":[22,11,12,13,22,12,28,14,15,24,28,15,26,18,19,23,22,13,25,16,17,20,26,19,2,26,20,0,2,20,0,20,21,30,17,18,30,18,26,25,17,30,10,11,22,16,24,15,29,16,25,29,24,16,1,2,0,9,22,23,10,22,9,8,28,24,8,24,29,13,14,28,28,23,13,8,23,28,9,23,8,31,25,30,27,29,25,31,27,25,7,8,29,3,30,26,3,26,2,31,30,3,27,7,29,4,31,3,6,7,27,5,31,4,27,31,5,6,27,5],"vertices":[1,12,16.85,-2.36,1,1,12,16.85,-16.43,1,2,12,-0.23,-13.38,0.99623,11,59.52,-9.37,0.00377,2,12,-11.9,-40.87,0.73223,11,47.85,-36.87,0.26777,2,12,-22.77,-47.07,0.56771,11,36.99,-43.07,0.43229,2,12,-32.97,-52.87,0.41882,11,26.78,-48.87,0.58118,3,12,-58.2,-50.88,0.18343,11,1.55,-46.87,0.81638,10,61.31,-49.95,0.00019,3,12,-64.37,-42.62,0.1301,11,-4.62,-38.62,0.86361,10,55.13,-41.7,0.00629,3,12,-77.39,-25.08,0.01154,11,-17.64,-21.07,0.82026,10,42.11,-24.15,0.1682,2,11,-37.8,-18.9,0.44257,10,21.95,-21.98,0.55743,2,11,-64.31,-5.41,0.00759,10,-4.56,-8.49,0.9924,1,10,-4.56,4.15,1,2,11,-64.31,23.94,0.00708,10,-4.56,20.86,0.99292,2,11,-33.11,23.94,0.42776,10,26.64,20.86,0.57224,2,11,-19.35,23.94,0.70252,10,40.41,20.86,0.29748,3,12,-62.1,19.8,0.02934,11,-2.35,23.81,0.90853,10,57.4,20.73,0.06212,3,12,-48.1,19.04,0.20654,11,11.65,23.04,0.79213,10,71.4,19.96,0.00133,2,12,-37.69,17.87,0.47874,11,22.06,21.87,0.52126,2,12,-25.75,16.43,0.81197,11,34,20.43,0.18803,2,12,-13.94,15.74,0.97289,11,45.81,19.74,0.02711,1,12,-0.05,15.62,1,1,12,16.84,15.62,1,2,11,-54.75,2.14,0.04888,10,5,-0.94,0.95112,2,11,-33.76,-0.08,0.44437,10,25.99,-3.16,0.55563,2,11,-4.82,0.87,0.95795,10,54.93,-2.21,0.04205,2,12,-38.95,-10.3,0.40894,11,20.81,-6.3,0.59106,2,12,-14.33,-7.72,0.99037,11,45.42,-3.72,0.00963,2,12,-47.32,-34.46,0.24672,11,12.43,-30.45,0.75328,2,11,-17.71,1.82,0.76277,10,42.05,-1.26,0.23723,3,12,-52,-12.2,0.11679,11,7.76,-8.2,0.88319,10,67.51,-11.28,0.00002,2,12,-27.38,-12.52,0.72459,11,32.37,-8.52,0.27541,2,12,-36,-34.2,0.42591,11,23.76,-30.19,0.57409]}},"A_lv11":{"A_lv2":{"type":"mesh","path":"A_lian2","hull":19,"uvs":[1,0.75149,1,1,0.875,1,0.75,1,0.625,1,0.5,1,0.375,1,0.25,1,0.112,0.85092,0.00001,0.85091,0,0.44725,0.11038,0.27332,0.23375,0.20499,0.36525,0.24226,0.5,0,0.625,0,0.75,0,0.85875,0.44725,0.99513,0.52179,0.1147,0.61483,0.23979,0.62105,0.37301,0.5962,0.50623,0.47818,0.62645,0.54651,0.73205,0.67074,0.87664,0.8074],"triangles":[7,8,20,8,19,20,8,9,19,9,10,19,20,11,12,10,11,19,20,19,11,22,5,21,7,21,6,5,6,21,7,20,21,20,13,21,20,12,13,21,13,22,13,14,22,4,24,3,4,23,24,4,5,23,5,22,23,17,24,16,22,15,23,24,23,16,23,15,16,22,14,15,2,25,1,25,0,1,2,3,25,3,24,25,24,17,25,25,18,0,25,17,18],"vertices":[1,7,26.25,3.34,1,1,7,26.25,-17.79,1,2,7,-14.17,-17.82,0.98787,8,58.67,-37.64,0.01213,2,7,-46.58,-19.05,0.5116,8,26.26,-38.88,0.4884,3,7,-79.42,-20.22,0.05978,8,-6.58,-40.04,0.85015,6,77.03,-37.03,0.09006,2,8,-46.17,-40.2,0.44108,6,37.44,-37.18,0.55892,3,8,-86.8,-40.2,0.04131,6,-3.19,-37.18,0.90163,5,85.66,-33.73,0.05707,2,6,-43.81,-37.18,0.58793,5,45.03,-33.73,0.41207,2,6,-88.66,-24.51,0.04446,5,0.18,-21.06,0.95554,1,5,-36.21,-21.06,1,1,5,-36.22,13.25,1,2,6,-89.19,24.59,0.05116,5,-0.34,28.03,0.94884,2,6,-49.09,30.39,0.48238,5,39.75,33.84,0.51762,3,8,-89.97,24.21,0.04001,6,-6.35,27.23,0.90354,5,82.49,30.67,0.05644,2,8,-46.17,44.8,0.54187,6,37.44,47.82,0.45813,3,7,-78.64,64.67,0.0148,8,-5.81,44.84,0.89048,6,77.81,47.86,0.09472,3,7,-40.94,65.1,0.18442,8,31.9,45.28,0.8155,6,115.51,48.3,0.00008,2,7,-16.58,28.74,0.82165,8,56.25,8.91,0.17835,1,7,24.66,22.86,1,2,6,-87.78,-4.44,0.00574,5,1.06,-0.99,0.99426,2,6,-47.13,-4.97,0.50855,5,41.72,-1.52,0.49145,2,6,-3.83,-2.86,0.97987,5,85.01,0.59,0.02013,2,8,-44.15,4.16,0.49196,6,39.46,7.17,0.50804,2,8,-5.08,-1.65,0.97378,6,78.54,1.37,0.02622,2,7,-49.73,8.54,0.35602,8,23.1,-11.29,0.64398,1,7,-13.85,-1.42,1]}},"A_lv7":{"A_lv5":{"path":"A_lian5","x":3.41,"y":1.03,"width":208,"height":207}},"A_lv8":{"A_lv3":{"path":"A_lian3","x":0.12,"y":-0.43,"width":24,"height":24}},"A_lv9":{"A_lv4":{"path":"A_lian4","x":-0.01,"y":0.81,"width":277,"height":277}}}},{"name":"2","attachments":{"A_lv1_wu_qi3":{"A_lv1":{"path":"A_zi1","x":1.87,"y":-24.76,"width":604,"height":554}},"A_lv12":{"A_lv5":{"path":"A_zi5","x":3.41,"y":1.03,"width":208,"height":207}},"A_lv13":{"A_lv4":{"path":"A_zi4","x":-0.01,"y":0.81,"width":277,"height":277}},"A_lv14":{"A_lv3":{"path":"A_zi3","x":0.12,"y":-0.43,"width":24,"height":24}},"A_lv15":{"A_lv6":{"type":"mesh","path":"A_zi6","hull":22,"uvs":[1,0.2532,1,0.45133,0.89019,0.40863,0.78981,0.81189,0.70425,0.90922,0.62446,0.99999,0.43995,0.98614,0.39523,0.87313,0.30029,0.63324,0.16994,0.60332,0,0.41327,0,0.23528,0,0,0.2,0,0.28824,0,0.4,0,0.5069,0,0.6,0,0.70875,0,0.8,0,0.89167,0,0.99999,0.00001,0.0613,0.30695,0.19584,0.3383,0.38134,0.32486,0.58518,0.401,0.79922,0.32934,0.5158,0.75106,0.29875,0.31147,0.47326,0.44544,0.68983,0.41311,0.60572,0.73649],"triangles":[22,11,12,13,22,12,28,14,15,24,28,15,26,18,19,23,22,13,25,16,17,20,26,19,2,26,20,0,2,20,0,20,21,30,17,18,30,18,26,25,17,30,10,11,22,16,24,15,29,16,25,29,24,16,1,2,0,9,22,23,10,22,9,8,28,24,8,24,29,13,14,28,28,23,13,8,23,28,9,23,8,31,25,30,27,29,25,31,27,25,7,8,29,3,30,26,3,26,2,31,30,3,27,7,29,4,31,3,6,7,27,5,31,4,27,31,5,6,27,5],"vertices":[1,12,16.85,-2.36,1,1,12,16.85,-16.43,1,2,12,-0.23,-13.38,0.99623,11,59.52,-9.37,0.00377,2,12,-11.9,-40.87,0.73223,11,47.85,-36.87,0.26777,2,12,-22.77,-47.07,0.56771,11,36.99,-43.07,0.43229,2,12,-32.97,-52.87,0.41882,11,26.78,-48.87,0.58118,3,12,-58.2,-50.88,0.18343,11,1.55,-46.87,0.81638,10,61.31,-49.95,0.00019,3,12,-64.37,-42.62,0.1301,11,-4.62,-38.62,0.86361,10,55.13,-41.7,0.00629,3,12,-77.39,-25.08,0.01154,11,-17.64,-21.07,0.82026,10,42.11,-24.15,0.1682,2,11,-37.8,-18.9,0.44257,10,21.95,-21.98,0.55743,2,11,-64.31,-5.41,0.00759,10,-4.56,-8.49,0.9924,1,10,-4.56,4.15,1,2,11,-64.31,23.94,0.00708,10,-4.56,20.86,0.99292,2,11,-33.11,23.94,0.42776,10,26.64,20.86,0.57224,2,11,-19.35,23.94,0.70252,10,40.41,20.86,0.29748,3,12,-62.1,19.8,0.02934,11,-2.35,23.81,0.90853,10,57.4,20.73,0.06212,3,12,-48.1,19.04,0.20654,11,11.65,23.04,0.79213,10,71.4,19.96,0.00133,2,12,-37.69,17.87,0.47874,11,22.06,21.87,0.52126,2,12,-25.75,16.43,0.81197,11,34,20.43,0.18803,2,12,-13.94,15.74,0.97289,11,45.81,19.74,0.02711,1,12,-0.05,15.62,1,1,12,16.84,15.62,1,2,11,-54.75,2.14,0.04888,10,5,-0.94,0.95112,2,11,-33.76,-0.08,0.44437,10,25.99,-3.16,0.55563,2,11,-4.82,0.87,0.95795,10,54.93,-2.21,0.04205,2,12,-38.95,-10.3,0.40894,11,20.81,-6.3,0.59106,2,12,-14.33,-7.72,0.99037,11,45.42,-3.72,0.00963,2,12,-47.32,-34.46,0.24672,11,12.43,-30.45,0.75328,2,11,-17.71,1.82,0.76277,10,42.05,-1.26,0.23723,3,12,-52,-12.2,0.11679,11,7.76,-8.2,0.88319,10,67.51,-11.28,0.00002,2,12,-27.38,-12.52,0.72459,11,32.37,-8.52,0.27541,2,12,-36,-34.2,0.42591,11,23.76,-30.19,0.57409]}},"A_lv16":{"A_lv2":{"type":"mesh","path":"A_zi2","hull":19,"uvs":[1,0.75149,1,1,0.875,1,0.75,1,0.625,1,0.5,1,0.375,1,0.25,1,0.112,0.85092,0.00001,0.85091,0,0.44725,0.11038,0.27332,0.23375,0.20499,0.36525,0.24226,0.5,0,0.625,0,0.75,0,0.85875,0.44725,0.99513,0.52179,0.1147,0.61483,0.23979,0.62105,0.37301,0.5962,0.50623,0.47818,0.62645,0.54651,0.73205,0.67074,0.87664,0.8074],"triangles":[7,8,20,8,19,20,8,9,19,9,10,19,20,11,12,10,11,19,20,19,11,22,5,21,7,21,6,5,6,21,7,20,21,20,13,21,20,12,13,21,13,22,13,14,22,4,24,3,4,23,24,4,5,23,5,22,23,17,24,16,22,15,23,24,23,16,23,15,16,22,14,15,2,25,1,25,0,1,2,3,25,3,24,25,24,17,25,25,18,0,25,17,18],"vertices":[1,7,26.25,3.34,1,1,7,26.25,-17.79,1,2,7,-14.17,-17.82,0.98787,8,58.67,-37.64,0.01213,2,7,-46.58,-19.05,0.5116,8,26.26,-38.88,0.4884,3,7,-79.42,-20.22,0.05978,8,-6.58,-40.04,0.85015,6,77.03,-37.03,0.09006,2,8,-46.17,-40.2,0.44108,6,37.44,-37.18,0.55892,3,8,-86.8,-40.2,0.04131,6,-3.19,-37.18,0.90163,5,85.66,-33.73,0.05707,2,6,-43.81,-37.18,0.58793,5,45.03,-33.73,0.41207,2,6,-88.66,-24.51,0.04446,5,0.18,-21.06,0.95554,1,5,-36.21,-21.06,1,1,5,-36.22,13.25,1,2,6,-89.19,24.59,0.05116,5,-0.34,28.03,0.94884,2,6,-49.09,30.39,0.48238,5,39.75,33.84,0.51762,3,8,-89.97,24.21,0.04001,6,-6.35,27.23,0.90354,5,82.49,30.67,0.05644,2,8,-46.17,44.8,0.54187,6,37.44,47.82,0.45813,3,7,-78.64,64.67,0.0148,8,-5.81,44.84,0.89048,6,77.81,47.86,0.09472,3,7,-40.94,65.1,0.18442,8,31.9,45.28,0.8155,6,115.51,48.3,0.00008,2,7,-16.58,28.74,0.82165,8,56.25,8.91,0.17835,1,7,24.66,22.86,1,2,6,-87.78,-4.44,0.00574,5,1.06,-0.99,0.99426,2,6,-47.13,-4.97,0.50855,5,41.72,-1.52,0.49145,2,6,-3.83,-2.86,0.97987,5,85.01,0.59,0.02013,2,8,-44.15,4.16,0.49196,6,39.46,7.17,0.50804,2,8,-5.08,-1.65,0.97378,6,78.54,1.37,0.02622,2,7,-49.73,8.54,0.35602,8,23.1,-11.29,0.64398,1,7,-13.85,-1.42,1]}},"A_guang_quan3":{"A_guang_quan":{"color":"e7b8ffff","x":3.25,"y":3.32,"width":241,"height":242}}}},{"name":"3","attachments":{"A_lv20":{"A_lv6":{"type":"mesh","path":"A_jin6","hull":22,"uvs":[1,0.2532,1,0.45133,0.89019,0.40863,0.78981,0.81189,0.70425,0.90922,0.62446,0.99999,0.43995,0.98614,0.39523,0.87313,0.30029,0.63324,0.16994,0.60332,0,0.41327,0,0.23528,0,0,0.2,0,0.28824,0,0.4,0,0.5069,0,0.6,0,0.70875,0,0.8,0,0.89167,0,0.99999,0.00001,0.0613,0.30695,0.19584,0.3383,0.38134,0.32486,0.58518,0.401,0.79922,0.32934,0.5158,0.75106,0.29875,0.31147,0.47326,0.44544,0.68983,0.41311,0.60572,0.73649],"triangles":[22,11,12,13,22,12,28,14,15,24,28,15,26,18,19,23,22,13,25,16,17,20,26,19,2,26,20,0,2,20,0,20,21,30,17,18,30,18,26,25,17,30,10,11,22,16,24,15,29,16,25,29,24,16,1,2,0,9,22,23,10,22,9,8,28,24,8,24,29,13,14,28,28,23,13,8,23,28,9,23,8,31,25,30,27,29,25,31,27,25,7,8,29,3,30,26,3,26,2,31,30,3,27,7,29,4,31,3,6,7,27,5,31,4,27,31,5,6,27,5],"vertices":[1,12,16.85,-2.36,1,1,12,16.85,-16.43,1,2,12,-0.23,-13.38,0.99623,11,59.52,-9.37,0.00377,2,12,-11.9,-40.87,0.73223,11,47.85,-36.87,0.26777,2,12,-22.77,-47.07,0.56771,11,36.99,-43.07,0.43229,2,12,-32.97,-52.87,0.41882,11,26.78,-48.87,0.58118,3,12,-58.2,-50.88,0.18343,11,1.55,-46.87,0.81638,10,61.31,-49.95,0.00019,3,12,-64.37,-42.62,0.1301,11,-4.62,-38.62,0.86361,10,55.13,-41.7,0.00629,3,12,-77.39,-25.08,0.01154,11,-17.64,-21.07,0.82026,10,42.11,-24.15,0.1682,2,11,-37.8,-18.9,0.44257,10,21.95,-21.98,0.55743,2,11,-64.31,-5.41,0.00759,10,-4.56,-8.49,0.9924,1,10,-4.56,4.15,1,2,11,-64.31,23.94,0.00708,10,-4.56,20.86,0.99292,2,11,-33.11,23.94,0.42776,10,26.64,20.86,0.57224,2,11,-19.35,23.94,0.70252,10,40.41,20.86,0.29748,3,12,-62.1,19.8,0.02934,11,-2.35,23.81,0.90853,10,57.4,20.73,0.06212,3,12,-48.1,19.04,0.20654,11,11.65,23.04,0.79213,10,71.4,19.96,0.00133,2,12,-37.69,17.87,0.47874,11,22.06,21.87,0.52126,2,12,-25.75,16.43,0.81197,11,34,20.43,0.18803,2,12,-13.94,15.74,0.97289,11,45.81,19.74,0.02711,1,12,-0.05,15.62,1,1,12,16.84,15.62,1,2,11,-54.75,2.14,0.04888,10,5,-0.94,0.95112,2,11,-33.76,-0.08,0.44437,10,25.99,-3.16,0.55563,2,11,-4.82,0.87,0.95795,10,54.93,-2.21,0.04205,2,12,-38.95,-10.3,0.40894,11,20.81,-6.3,0.59106,2,12,-14.33,-7.72,0.99037,11,45.42,-3.72,0.00963,2,12,-47.32,-34.46,0.24672,11,12.43,-30.45,0.75328,2,11,-17.71,1.82,0.76277,10,42.05,-1.26,0.23723,3,12,-52,-12.2,0.11679,11,7.76,-8.2,0.88319,10,67.51,-11.28,0.00002,2,12,-27.38,-12.52,0.72459,11,32.37,-8.52,0.27541,2,12,-36,-34.2,0.42591,11,23.76,-30.19,0.57409]}},"A_lv21":{"A_lv2":{"type":"mesh","path":"A_jin2","hull":19,"uvs":[1,0.75149,1,1,0.875,1,0.75,1,0.625,1,0.5,1,0.375,1,0.25,1,0.112,0.85092,0.00001,0.85091,0,0.44725,0.11038,0.27332,0.23375,0.20499,0.36525,0.24226,0.5,0,0.625,0,0.75,0,0.85875,0.44725,0.99513,0.52179,0.1147,0.61483,0.23979,0.62105,0.37301,0.5962,0.50623,0.47818,0.62645,0.54651,0.73205,0.67074,0.87664,0.8074],"triangles":[7,8,20,8,19,20,8,9,19,9,10,19,20,11,12,10,11,19,20,19,11,22,5,21,7,21,6,5,6,21,7,20,21,20,13,21,20,12,13,21,13,22,13,14,22,4,24,3,4,23,24,4,5,23,5,22,23,17,24,16,22,15,23,24,23,16,23,15,16,22,14,15,2,25,1,25,0,1,2,3,25,3,24,25,24,17,25,25,18,0,25,17,18],"vertices":[1,7,26.25,3.34,1,1,7,26.25,-17.79,1,2,7,-14.17,-17.82,0.98787,8,58.67,-37.64,0.01213,2,7,-46.58,-19.05,0.5116,8,26.26,-38.88,0.4884,3,7,-79.42,-20.22,0.05978,8,-6.58,-40.04,0.85015,6,77.03,-37.03,0.09006,2,8,-46.17,-40.2,0.44108,6,37.44,-37.18,0.55892,3,8,-86.8,-40.2,0.04131,6,-3.19,-37.18,0.90163,5,85.66,-33.73,0.05707,2,6,-43.81,-37.18,0.58793,5,45.03,-33.73,0.41207,2,6,-88.66,-24.51,0.04446,5,0.18,-21.06,0.95554,1,5,-36.21,-21.06,1,1,5,-36.22,13.25,1,2,6,-89.19,24.59,0.05116,5,-0.34,28.03,0.94884,2,6,-49.09,30.39,0.48238,5,39.75,33.84,0.51762,3,8,-89.97,24.21,0.04001,6,-6.35,27.23,0.90354,5,82.49,30.67,0.05644,2,8,-46.17,44.8,0.54187,6,37.44,47.82,0.45813,3,7,-78.64,64.67,0.0148,8,-5.81,44.84,0.89048,6,77.81,47.86,0.09472,3,7,-40.94,65.1,0.18442,8,31.9,45.28,0.8155,6,115.51,48.3,0.00008,2,7,-16.58,28.74,0.82165,8,56.25,8.91,0.17835,1,7,24.66,22.86,1,2,6,-87.78,-4.44,0.00574,5,1.06,-0.99,0.99426,2,6,-47.13,-4.97,0.50855,5,41.72,-1.52,0.49145,2,6,-3.83,-2.86,0.97987,5,85.01,0.59,0.02013,2,8,-44.15,4.16,0.49196,6,39.46,7.17,0.50804,2,8,-5.08,-1.65,0.97378,6,78.54,1.37,0.02622,2,7,-49.73,8.54,0.35602,8,23.1,-11.29,0.64398,1,7,-13.85,-1.42,1]}},"A_lv1_wu_qi4":{"A_lv1":{"path":"A_jin1","x":1.87,"y":-35.25,"width":604,"height":521}},"A_lv17":{"A_lv5":{"path":"A_jin5","x":3.41,"y":1.03,"width":208,"height":207}},"A_lv18":{"A_lv4":{"path":"A_jin4","x":-0.01,"y":0.81,"width":277,"height":277}},"A_lv19":{"A_lv3":{"path":"A_jin3","x":0.12,"y":-0.43,"width":24,"height":24}},"A_guang_quan4":{"A_guang_quan":{"color":"f2ff7cff","x":3.25,"y":3.32,"width":241,"height":242}}}},{"name":"4","attachments":{"A_lv22":{"A_lv5":{"path":"A_hong5","x":3.41,"y":1.03,"width":208,"height":207}},"A_lv23":{"A_lv4":{"path":"A_hong4","x":-0.01,"y":0.81,"width":277,"height":277}},"A_lv24":{"A_lv3":{"path":"A_hong3","x":0.12,"y":-0.43,"width":24,"height":24}},"A_lv25":{"A_lv6":{"type":"mesh","path":"A_hong6","hull":22,"uvs":[1,0.2532,1,0.45133,0.89019,0.40863,0.78981,0.81189,0.70425,0.90922,0.62446,0.99999,0.43995,0.98614,0.39523,0.87313,0.30029,0.63324,0.16994,0.60332,0,0.41327,0,0.23528,0,0,0.2,0,0.28824,0,0.4,0,0.5069,0,0.6,0,0.70875,0,0.8,0,0.89167,0,0.99999,0.00001,0.0613,0.30695,0.19584,0.3383,0.38134,0.32486,0.58518,0.401,0.79922,0.32934,0.5158,0.75106,0.29875,0.31147,0.47326,0.44544,0.68983,0.41311,0.60572,0.73649],"triangles":[22,11,12,13,22,12,28,14,15,24,28,15,26,18,19,23,22,13,25,16,17,20,26,19,2,26,20,0,2,20,0,20,21,30,17,18,30,18,26,25,17,30,10,11,22,16,24,15,29,16,25,29,24,16,1,2,0,9,22,23,10,22,9,8,28,24,8,24,29,13,14,28,28,23,13,8,23,28,9,23,8,31,25,30,27,29,25,31,27,25,7,8,29,3,30,26,3,26,2,31,30,3,27,7,29,4,31,3,6,7,27,5,31,4,27,31,5,6,27,5],"vertices":[1,12,16.85,-2.36,1,1,12,16.85,-16.43,1,2,12,-0.23,-13.38,0.99623,11,59.52,-9.37,0.00377,2,12,-11.9,-40.87,0.73223,11,47.85,-36.87,0.26777,2,12,-22.77,-47.07,0.56771,11,36.99,-43.07,0.43229,2,12,-32.97,-52.87,0.41882,11,26.78,-48.87,0.58118,3,12,-58.2,-50.88,0.18343,11,1.55,-46.87,0.81638,10,61.31,-49.95,0.00019,3,12,-64.37,-42.62,0.1301,11,-4.62,-38.62,0.86361,10,55.13,-41.7,0.00629,3,12,-77.39,-25.08,0.01154,11,-17.64,-21.07,0.82026,10,42.11,-24.15,0.1682,2,11,-37.8,-18.9,0.44257,10,21.95,-21.98,0.55743,2,11,-64.31,-5.41,0.00759,10,-4.56,-8.49,0.9924,1,10,-4.56,4.15,1,2,11,-64.31,23.94,0.00708,10,-4.56,20.86,0.99292,2,11,-33.11,23.94,0.42776,10,26.64,20.86,0.57224,2,11,-19.35,23.94,0.70252,10,40.41,20.86,0.29748,3,12,-62.1,19.8,0.02934,11,-2.35,23.81,0.90853,10,57.4,20.73,0.06212,3,12,-48.1,19.04,0.20654,11,11.65,23.04,0.79213,10,71.4,19.96,0.00133,2,12,-37.69,17.87,0.47874,11,22.06,21.87,0.52126,2,12,-25.75,16.43,0.81197,11,34,20.43,0.18803,2,12,-13.94,15.74,0.97289,11,45.81,19.74,0.02711,1,12,-0.05,15.62,1,1,12,16.84,15.62,1,2,11,-54.75,2.14,0.04888,10,5,-0.94,0.95112,2,11,-33.76,-0.08,0.44437,10,25.99,-3.16,0.55563,2,11,-4.82,0.87,0.95795,10,54.93,-2.21,0.04205,2,12,-38.95,-10.3,0.40894,11,20.81,-6.3,0.59106,2,12,-14.33,-7.72,0.99037,11,45.42,-3.72,0.00963,2,12,-47.32,-34.46,0.24672,11,12.43,-30.45,0.75328,2,11,-17.71,1.82,0.76277,10,42.05,-1.26,0.23723,3,12,-52,-12.2,0.11679,11,7.76,-8.2,0.88319,10,67.51,-11.28,0.00002,2,12,-27.38,-12.52,0.72459,11,32.37,-8.52,0.27541,2,12,-36,-34.2,0.42591,11,23.76,-30.19,0.57409]}},"A_lv26":{"A_lv2":{"type":"mesh","path":"A_hong2","hull":19,"uvs":[1,0.75149,1,1,0.875,1,0.75,1,0.625,1,0.5,1,0.375,1,0.25,1,0.112,0.85092,0.00001,0.85091,0,0.44725,0.11038,0.27332,0.23375,0.20499,0.36525,0.24226,0.5,0,0.625,0,0.75,0,0.85875,0.44725,0.99513,0.52179,0.1147,0.61483,0.23979,0.62105,0.37301,0.5962,0.50623,0.47818,0.62645,0.54651,0.73205,0.67074,0.87664,0.8074],"triangles":[7,8,20,8,19,20,8,9,19,9,10,19,20,11,12,10,11,19,20,19,11,22,5,21,7,21,6,5,6,21,7,20,21,20,13,21,20,12,13,21,13,22,13,14,22,4,24,3,4,23,24,4,5,23,5,22,23,17,24,16,22,15,23,24,23,16,23,15,16,22,14,15,2,25,1,25,0,1,2,3,25,3,24,25,24,17,25,25,18,0,25,17,18],"vertices":[1,7,26.25,3.34,1,1,7,26.25,-17.79,1,2,7,-14.17,-17.82,0.98787,8,58.67,-37.64,0.01213,2,7,-46.58,-19.05,0.5116,8,26.26,-38.88,0.4884,3,7,-79.42,-20.22,0.05978,8,-6.58,-40.04,0.85015,6,77.03,-37.03,0.09006,2,8,-46.17,-40.2,0.44108,6,37.44,-37.18,0.55892,3,8,-86.8,-40.2,0.04131,6,-3.19,-37.18,0.90163,5,85.66,-33.73,0.05707,2,6,-43.81,-37.18,0.58793,5,45.03,-33.73,0.41207,2,6,-88.66,-24.51,0.04446,5,0.18,-21.06,0.95554,1,5,-36.21,-21.06,1,1,5,-36.22,13.25,1,2,6,-89.19,24.59,0.05116,5,-0.34,28.03,0.94884,2,6,-49.09,30.39,0.48238,5,39.75,33.84,0.51762,3,8,-89.97,24.21,0.04001,6,-6.35,27.23,0.90354,5,82.49,30.67,0.05644,2,8,-46.17,44.8,0.54187,6,37.44,47.82,0.45813,3,7,-78.64,64.67,0.0148,8,-5.81,44.84,0.89048,6,77.81,47.86,0.09472,3,7,-40.94,65.1,0.18442,8,31.9,45.28,0.8155,6,115.51,48.3,0.00008,2,7,-16.58,28.74,0.82165,8,56.25,8.91,0.17835,1,7,24.66,22.86,1,2,6,-87.78,-4.44,0.00574,5,1.06,-0.99,0.99426,2,6,-47.13,-4.97,0.50855,5,41.72,-1.52,0.49145,2,6,-3.83,-2.86,0.97987,5,85.01,0.59,0.02013,2,8,-44.15,4.16,0.49196,6,39.46,7.17,0.50804,2,8,-5.08,-1.65,0.97378,6,78.54,1.37,0.02622,2,7,-49.73,8.54,0.35602,8,23.1,-11.29,0.64398,1,7,-13.85,-1.42,1]}},"A_lv1_wu_qi5":{"A_lv1":{"path":"A_hong1","x":1.87,"y":-24.76,"width":604,"height":543}},"A_guang_quan5":{"A_guang_quan":{"color":"ff6d84ff","x":3.25,"y":3.32,"width":241,"height":242}}}}],"animations":{"idle":{"slots":{"A_guang_quan5":{"color":[{"color":"ffffff00"},{"time":0.4,"color":"ffffffff"},{"time":0.9333,"color":"ffffff00"}]},"A_lv1_wu_qi":{"color":[{"color":"ffffffe5","curve":0.25,"c3":0.75},{"time":1,"color":"ffffffff","curve":0.25,"c3":0.75},{"time":2,"color":"ffffffe5"}]},"A_lv1_wu_qi4":{"color":[{"color":"ffffffe5","curve":0.25,"c3":0.75},{"time":1,"color":"ffffffff","curve":0.25,"c3":0.75},{"time":2,"color":"ffffffe5"}]},"A_guang_quan":{"color":[{"color":"ffffff00"},{"time":0.4,"color":"ffffffff"},{"time":0.9333,"color":"ffffff00"}]},"A_guang_quan4":{"color":[{"color":"ffffff00"},{"time":0.4,"color":"ffffffff"},{"time":0.9333,"color":"ffffff00"}]},"A_lv1_wu_qi3":{"color":[{"color":"ffffffe5","curve":0.25,"c3":0.75},{"time":1,"color":"ffffffff","curve":0.25,"c3":0.75},{"time":2,"color":"ffffffe5"}]},"A_lv1_wu_qi2":{"color":[{"color":"ffffffe5","curve":0.25,"c3":0.75},{"time":1,"color":"ffffffff","curve":0.25,"c3":0.75},{"time":2,"color":"ffffffe5"}]},"A_guang_quan3":{"color":[{"color":"ffffff00"},{"time":0.4,"color":"ffffffff"},{"time":0.9333,"color":"ffffff00"}]},"A_guang_quan2":{"color":[{"color":"ffffff00"},{"time":0.4,"color":"ffffffff"},{"time":0.9333,"color":"ffffff00"}]},"A_lv1_wu_qi5":{"color":[{"color":"ffffffe5","curve":0.25,"c3":0.75},{"time":1,"color":"ffffffff","curve":0.25,"c3":0.75},{"time":2,"color":"ffffffe5"}]}},"bones":{"A_lv4":{"rotate":[{},{"time":1,"angle":180},{"time":2}],"scale":[{"curve":0.25,"c3":0.75},{"time":1,"x":1.08,"y":1.08,"curve":0.25,"c3":0.75},{"time":2}]},"bone2":{"translate":[{"x":-41.62,"y":5.2,"curve":0.25,"c3":0.75},{"time":1,"curve":0.25,"c3":0.75},{"time":2,"x":-41.62,"y":5.2}]},"bone3":{"translate":[{"y":13.27,"curve":0.25,"c3":0.75},{"time":1,"curve":0.25,"c3":0.75},{"time":2,"y":13.27}]},"bone4":{"translate":[{"y":-8.49,"curve":0.371,"c2":0.62,"c3":0.71},{"time":0.1667,"y":-9.4,"curve":0.25,"c3":0.75},{"time":1.1667,"curve":0.243,"c3":0.689,"c4":0.75},{"time":2,"y":-8.49}]},"bone5":{"translate":[{"y":-8.02,"curve":0.375,"c2":0.5,"c3":0.75},{"time":0.5,"y":-16.04,"curve":0.25,"c3":0.75},{"time":1.5,"curve":0.25,"c3":0.625,"c4":0.5},{"time":2,"y":-8.02}]},"bone6":{"translate":[{"y":8.32,"curve":0.382,"c2":0.57,"c3":0.735},{"time":0.3333,"y":11.61,"curve":0.25,"c3":0.75},{"time":1.3333,"curve":0.243,"c3":0.649,"c4":0.6},{"time":2,"y":8.32}]},"A_lv6":{"translate":[{"x":45.75,"y":1.82,"curve":0.25,"c3":0.75},{"time":1,"x":11.17,"y":19.39,"curve":0.25,"c3":0.75},{"time":2,"x":45.75,"y":1.82}]},"A_lv7":{"translate":[{"y":-10.74,"curve":0.25,"c3":0.75},{"time":1,"curve":0.25,"c3":0.75},{"time":2,"y":-10.74}]},"A_lv8":{"translate":[{"y":13.54,"curve":0.371,"c2":0.62,"c3":0.71},{"time":0.1667,"y":16.77,"curve":0.25,"c3":0.75},{"time":1.1667,"y":-16.77,"curve":0.243,"c3":0.689,"c4":0.75},{"time":2,"y":13.54}]},"A_lv9":{"translate":[{"y":-4.64,"curve":0.382,"c2":0.57,"c3":0.735},{"time":0.3333,"y":-10.74,"curve":0.25,"c3":0.75},{"time":1.3333,"y":10.74,"curve":0.243,"c3":0.649,"c4":0.6},{"time":2,"y":-4.64}]},"bone7":{"scale":[{"curve":0.25,"c3":0.75},{"time":0.9333,"x":1.503,"y":1.503}]}}}}},[0]]],0,0,[0],[-1],[0]]